README.md
setup.cfg
setup.py
SPWS_2010/Framework.py
SPWS_2010/config.py
SPWS_2010.egg-info/PKG-INFO
SPWS_2010.egg-info/SOURCES.txt
SPWS_2010.egg-info/dependency_links.txt
SPWS_2010.egg-info/requires.txt
SPWS_2010.egg-info/top_level.txt